docker_model_runner/__init__.py
docker_model_runner/async_client.py
docker_model_runner/client.py
docker_model_runner-0.1.2.dist-info/licenses/LICENSE
docker_model_runner-0.1.2.dist-info/METADATA
docker_model_runner-0.1.2.dist-info/WHEEL
docker_model_runner-0.1.2.dist-info/top_level.txt
docker_model_runner-0.1.2.dist-info/RECORD
