Metadata-Version: 2.4
Name: docker-model-runner
Version: 0.1.2
Summary: Python Client for Docker Model Runner
Author: Docker Model Runner Team
License: MIT
Project-URL: Homepage, https://github.com/AIMLDev726/docker_model_runner_python_client
Project-URL: Repository, https://github.com/AIMLDev726/docker_model_runner_python_client
Classifier: Development Status :: 4 - Beta
Classifier: Intended Audience :: Developers
Classifier: License :: OSI Approved :: MIT License
Classifier: Programming Language :: Python :: 3
Classifier: Programming Language :: Python :: 3.7
Classifier: Programming Language :: Python :: 3.8
Classifier: Programming Language :: Python :: 3.9
Classifier: Programming Language :: Python :: 3.10
Classifier: Programming Language :: Python :: 3.11
Classifier: Programming Language :: Python :: 3.12
Requires-Python: >=3.7
License-File: LICENSE
Requires-Dist: requests>=2.25.0
Requires-Dist: aiohttp>=3.8.0
Requires-Dist: pydantic>=1.8.0
Requires-Dist: typing-extensions>=4.0.0
Requires-Dist: fastmcp>=0.1.0
Requires-Dist: mcp>=1.13.1
Dynamic: license-file
